conversational_graph/__init__.py
conversational_graph/factory.py
videosdk_conversational_graph-0.0.5.dist-info/METADATA
videosdk_conversational_graph-0.0.5.dist-info/WHEEL
videosdk_conversational_graph-0.0.5.dist-info/top_level.txt
videosdk_conversational_graph-0.0.5.dist-info/RECORD
