Metadata-Version: 2.4
Name: videosdk-conversational-graph
Version: 0.0.5
Summary: Conversational graph package
Requires-Python: >=3.9
Dynamic: requires-python
